whereis/__init__.py
whereis/cli.py
whereis/whereis.py
whereis-0.0.2.dist-info/DESCRIPTION.rst
whereis-0.0.2.dist-info/METADATA
whereis-0.0.2.dist-info/RECORD
whereis-0.0.2.dist-info/WHEEL
whereis-0.0.2.dist-info/entry_points.txt
whereis-0.0.2.dist-info/metadata.json
whereis-0.0.2.dist-info/top_level.txt
