Metadata-Version: 2.0
Name: whereis
Version: 0.0.2
Summary: Platform independent whereis.
Home-page: https://github.com/draperjames/whereis
Author: James Draper
Author-email: draperjames@github.io
License: MIT license
Keywords: whereis
Platform: UNKNOWN
Classifier: Development Status :: 2 - Pre-Alpha
Classifier: Intended Audience :: Developers
Classifier: License :: OSI Approved :: MIT License
Classifier: Natural Language :: English
Classifier: Programming Language :: Python :: 2
Classifier: Programming Language :: Python :: 2.7
Classifier: Programming Language :: Python :: 3
Classifier: Programming Language :: Python :: 3.4
Classifier: Programming Language :: Python :: 3.5
Classifier: Programming Language :: Python :: 3.6
Requires-Dist: Click (>=6.0)
